LICENSE
tense/__init__.py
tense/adapters/__init__.py
tense/adapters/converters.py
tense/adapters/parsers.py
tense/adapters/repository.py
tense/application/__init__.py
tense/application/exceptions.py
tense/application/factory.py
tense/application/ports/converters.py
tense/application/ports/parsers.py
tense/application/ports/repository.py
tense/application/resolvers.py
tense/domain/model.py
tense/domain/units.py
tense/service_layer/__init__.py
tense/service_layer/dot_tense/__init__.py
tense/service_layer/dot_tense/converters.py
tense/service_layer/dot_tense/domain.py
tense/service_layer/dot_tense/exceptions.py
tense/service_layer/dot_tense/step_chain.py
tense/service_layer/safe_eval.py
tense/service_layer/unit_of_work.py
tense-1.0.1b0.dist-info/LICENSE
tense-1.0.1b0.dist-info/WHEEL
tense-1.0.1b0.dist-info/METADATA
tense-1.0.1b0.dist-info/RECORD
